collective.easynewsletter_combined_send-1.1-py3.8-nspkg.pth
collective/easynewsletter_combined_send/__init__.py
collective/easynewsletter_combined_send/configure.zcml
collective/easynewsletter_combined_send/interfaces.py
collective/easynewsletter_combined_send/issuedatafetcher.py
collective/easynewsletter_combined_send/overrides.zcml
collective/easynewsletter_combined_send/permissions.zcml
collective/easynewsletter_combined_send/setuphandlers.py
collective/easynewsletter_combined_send/testing.py
collective/easynewsletter_combined_send/browser/__init__.py
collective/easynewsletter_combined_send/browser/configure.zcml
collective/easynewsletter_combined_send/browser/overrides/.gitkeep
collective/easynewsletter_combined_send/browser/static/.gitkeep
collective/easynewsletter_combined_send/locales/README.rst
collective/easynewsletter_combined_send/locales/__init__.py
collective/easynewsletter_combined_send/locales/collective.easynewsletter_combined_send.pot
collective/easynewsletter_combined_send/locales/update.py
collective/easynewsletter_combined_send/locales/update.sh
collective/easynewsletter_combined_send/locales/en/LC_MESSAGES/collective.easynewsletter_combined_send.mo
collective/easynewsletter_combined_send/locales/en/LC_MESSAGES/collective.easynewsletter_combined_send.po
collective/easynewsletter_combined_send/profiles/default/browserlayer.xml
collective/easynewsletter_combined_send/profiles/default/catalog.xml
collective/easynewsletter_combined_send/profiles/default/metadata.xml
collective/easynewsletter_combined_send/profiles/default/rolemap.xml
collective/easynewsletter_combined_send/profiles/default/registry/main.xml
collective/easynewsletter_combined_send/profiles/uninstall/browserlayer.xml
collective/easynewsletter_combined_send/tests/__init__.py
collective/easynewsletter_combined_send/tests/test_issuedatafetcher.py
collective/easynewsletter_combined_send/tests/test_robot.py
collective/easynewsletter_combined_send/tests/test_setup.py
collective.easynewsletter_combined_send-1.1.dist-info/LICENSE.GPL
collective.easynewsletter_combined_send-1.1.dist-info/LICENSE.rst
collective.easynewsletter_combined_send-1.1.dist-info/METADATA
collective.easynewsletter_combined_send-1.1.dist-info/WHEEL
collective.easynewsletter_combined_send-1.1.dist-info/entry_points.txt
collective.easynewsletter_combined_send-1.1.dist-info/namespace_packages.txt
collective.easynewsletter_combined_send-1.1.dist-info/top_level.txt
collective.easynewsletter_combined_send-1.1.dist-info/RECORD
