Metadata-Version: 2.1
Name: collective.easynewsletter-combined-send
Version: 1.1
Summary: Extend EasyNewsletter to send languages combined one email.
Home-page: https://github.com/collective/collective.easynewsletter-combined-send
Author: Maik Derstappen
Author-email: md@derico.de
License: GPL version 2
Project-URL: PyPI, https://pypi.python.org/pypi/collective.easynewsletter-combined-send
Project-URL: Source, https://github.com/collective/collective.easynewsletter-combined-send
Project-URL: Tracker, https://github.com/collective/collective.easynewsletter-combined-send/issues
Keywords: Python Plone CMS
Platform: UNKNOWN
Classifier: Environment :: Web Environment
Classifier: Framework :: Plone
Classifier: Framework :: Plone :: Addon
Classifier: Framework :: Plone :: 5.2
Classifier: Programming Language :: Python
Classifier: Programming Language :: Python :: 2.7
Classifier: Programming Language :: Python :: 3.7
Classifier: Programming Language :: Python :: 3.8
Classifier: Programming Language :: Python :: 3.9
Classifier: Operating System :: OS Independent
Classifier: License :: OSI Approved :: GNU General Public License v2 (GPLv2)
Requires-Python: >=2.7,!=3.0.*,!=3.1.*,!=3.2.*,!=3.3.*,!=3.4.*,!=3.5.*,!=3.6.*
License-File: LICENSE.GPL
License-File: LICENSE.rst
Requires-Dist: setuptools
Requires-Dist: z3c.jbot
Requires-Dist: plone.api (>=1.8.4)
Requires-Dist: plone.restapi
Requires-Dist: plone.app.dexterity
Requires-Dist: Products.EasyNewsletter (>=5.0.7)
Requires-Dist: beautifulsoup4
Provides-Extra: test
Requires-Dist: plone.app.testing ; extra == 'test'
Requires-Dist: plone.testing (>=5.0.0) ; extra == 'test'
Requires-Dist: plone.app.contenttypes ; extra == 'test'
Requires-Dist: plone.app.robotframework[debug] ; extra == 'test'
